vigilant_scanner/__init__.py
vigilant_scanner/logger.py
vigilant_scanner/vgls.py
vigilant_scanner/log_analyzer/__init__.py
vigilant_scanner/log_analyzer/log_analyzer.py
vigilant_scanner/log_analyzer/patterns.json
vigilant_scanner/scanner/__init__.py
vigilant_scanner/scanner/db_manager.py
vigilant_scanner/scanner/metadata_collector.py
vigilant_scanner/scanner/report_generator.py
vigilant_scanner/scanner/scanner.py
vigilant_scanner-1.0.2.dist-info/METADATA
vigilant_scanner-1.0.2.dist-info/WHEEL
vigilant_scanner-1.0.2.dist-info/entry_points.txt
vigilant_scanner-1.0.2.dist-info/licenses/LICENSE
vigilant_scanner-1.0.2.dist-info/RECORD
