Metadata-Version: 2.4
Name: vigilant-scanner
Version: 1.0.2
Summary: A CLI tool for monitoring file integrity, detecting changes, analyzing logs and identifying potential security threats.
Project-URL: Homepage, https://github.com/ivpel/vigilant-scanner
Project-URL: Bug Tracker, https://github.com/ivpel/vigilant-scanner/issues
Author-email: Pelykh Ivan <ivan.pelykh@protonmail.com>
License-File: LICENSE
Keywords: change-detection,directory-scanning,file-integrity,infosec,malware-detection,monitoring,scanning,security
Requires-Python: >=3.10
Requires-Dist: rich
Requires-Dist: typer
Provides-Extra: dev
Requires-Dist: pytest; extra == 'dev'
